mlist/__init__.py
mlist/mohit.py
mlist-1.0.0.dist-info/LICENSE
mlist-1.0.0.dist-info/METADATA
mlist-1.0.0.dist-info/WHEEL
mlist-1.0.0.dist-info/top_level.txt
mlist-1.0.0.dist-info/RECORD
