Metadata-Version: 2.1
Name: mlist
Version: 1.0.0
Summary: A modified list 
Home-page: https://github.com/mohitraj/mlist
Author: Mohit
Author-email: mohitraj.cs@email.com
License: UNKNOWN
Platform: UNKNOWN
Classifier: Programming Language :: Python :: 3
Classifier: Operating System :: OS Independent
License-File: LICENSE
